sora/__init__.py
sora/_version.py
sora/body/__init__.py
sora/body/core.py
sora/body/meta.py
sora/body/utils.py
sora/body/values.py
sora/body/frame/__init__.py
sora/body/frame/core.py
sora/body/frame/iau_report.py
sora/body/frame/meta.py
sora/body/shape/__init__.py
sora/body/shape/core.py
sora/body/shape/limb.py
sora/body/shape/meta.py
sora/body/shape/utils.py
sora/config/__init__.py
sora/config/decorators.py
sora/config/input_tests.py
sora/config/list.py
sora/config/visuals.py
sora/data/sphere.obj
sora/ephem/__init__.py
sora/ephem/core.py
sora/ephem/meta.py
sora/ephem/miriade.py
sora/ephem/nima.py
sora/ephem/utils.py
sora/extra/__init__.py
sora/extra/chisquare.py
sora/extra/plots.py
sora/extra/utils.py
sora/lightcurve/__init__.py
sora/lightcurve/core.py
sora/lightcurve/occdetect.py
sora/lightcurve/utils.py
sora/observer/__init__.py
sora/observer/core.py
sora/observer/utils.py
sora/occultation/__init__.py
sora/occultation/chord.py
sora/occultation/chordlist.py
sora/occultation/core.py
sora/occultation/fitting.py
sora/occultation/meta.py
sora/occultation/utils.py
sora/prediction/__init__.py
sora/prediction/core.py
sora/prediction/occmap.py
sora/prediction/table.py
sora/prediction/values.py
sora/star/__init__.py
sora/star/catalog.py
sora/star/core.py
sora/star/meta.py
sora/star/utils.py
sora/stats/__init__.py
sora/stats/core.py
sora/stats/optimize.py
sora/tests/__init__.py
sora/tests/test_body_frame_iau_report.py
sora/tests/test_body_frame_meta.py
sora/tests/test_example.py
sora/tests/test_star_core.py
sora/tests/test_star_utils.py
sora_astro-0.3.2.post2.dist-info/licenses/LICENSE
sora_astro-0.3.2.post2.dist-info/METADATA
sora_astro-0.3.2.post2.dist-info/WHEEL
sora_astro-0.3.2.post2.dist-info/top_level.txt
sora_astro-0.3.2.post2.dist-info/RECORD
