Metadata-Version: 2.4
Name: sora-astro
Version: 0.3.2.post2
Summary: Stellar Occultation Library
Home-page: https://github.com/riogroup/SORA
Author: SORA Team
Author-email: rio.occteam@gmail.com
License: MIT
Project-URL: Bug Reports, https://github.com/riogroup/SORA/issues
Project-URL: Documentation, https://sora.readthedocs.io/
Keywords: science,astronomy,occultation
Classifier: Development Status :: 5 - Production/Stable
Classifier: Intended Audience :: Science/Research 
Classifier: License :: OSI Approved :: MIT License
Classifier: Programming Language :: Python :: 3.11
Classifier: Topic :: Scientific/Engineering :: Astronomy
Requires-Python: >=3.11, <4
License-File: LICENSE
Requires-Dist: numpy>=2.2
Requires-Dist: pyerfa>=2.0
Requires-Dist: astropy>=7.0
Requires-Dist: astroquery>=0.4.9
Requires-Dist: spiceypy>=6.0.0
Requires-Dist: matplotlib>=3.10.0
Requires-Dist: scipy>=1.15
Requires-Dist: requests
Requires-Dist: tqdm>=4.66
Requires-Dist: shapely>=2.0.7
Requires-Dist: cartopy>=0.24
Dynamic: author
Dynamic: author-email
Dynamic: classifier
Dynamic: description
Dynamic: description-content-type
Dynamic: home-page
Dynamic: keywords
Dynamic: license
Dynamic: license-file
Dynamic: project-url
Dynamic: requires-dist
Dynamic: requires-python
Dynamic: summary
